{
	"info": {
		"_postman_id": "3d3ed10a-7499-40a1-8f3b-9da60ccf54aa",
		"name": "Fortaleza de Sabor - API Completa",
		"description": "Collection completa para testar todos os endpoints da API Fortaleza de Sabor, incluindo gestão de usuários, restaurantes e autenticação.",
		"schema": "https://schema.getpostman.com/json/collection/v2.1.0/collection.json",
		"_exporter_id": "24546161"
	},
	"item": [
		{
			"name": "👤TypeUser",
			"item": [
				{
					"name": "1.TypeUser - Create (Cliente)",
					"request": {
						"method": "POST",
						"header": [],
						"body": {
							"mode": "raw",
							"raw": "{\r\n    \"nameType\": \"CLIENTE\"        \r\n}",
							"options": {
								"raw": {
									"language": "json"
								}
							}
						},
						"url": {
							"raw": "http://localhost:8080/typeUser",
							"protocol": "http",
							"host": [
								"localhost"
							],
							"port": "8080",
							"path": [
								"typeUser"
							]
						}
					},
					"response": []
				},
				{
					"name": "2.TypeUser - Create (Dono)",
					"request": {
						"method": "POST",
						"header": [],
						"body": {
							"mode": "raw",
							"raw": "{\r\n    \"nameType\": \"DONO\"        \r\n}",
							"options": {
								"raw": {
									"language": "json"
								}
							}
						},
						"url": {
							"raw": "http://localhost:8080/typeUser",
							"protocol": "http",
							"host": [
								"localhost"
							],
							"port": "8080",
							"path": [
								"typeUser"
							]
						}
					},
					"response": []
				},
				{
					"name": "3.TypeUser - Get All",
					"request": {
						"method": "GET",
						"header": [],
						"url": {
							"raw": "http://localhost:8080/typeUser",
							"protocol": "http",
							"host": [
								"localhost"
							],
							"port": "8080",
							"path": [
								"typeUser"
							]
						}
					},
					"response": []
				},
				{
					"name": "4.TypeUser - Get By Id",
					"request": {
						"method": "GET",
						"header": [],
						"url": {
							"raw": "http://localhost:8080/typeUser/1",
							"protocol": "http",
							"host": [
								"localhost"
							],
							"port": "8080",
							"path": [
								"typeUser",
								"1"
							]
						}
					},
					"response": []
				},
				{
					"name": "5.TypeUser - Update",
					"request": {
						"method": "PUT",
						"header": [],
						"body": {
							"mode": "raw",
							"raw": "{\r\n    \"nameType\": \"VISITANTE\"        \r\n}",
							"options": {
								"raw": {
									"language": "json"
								}
							}
						},
						"url": {
							"raw": "http://localhost:8080/typeUser/1",
							"protocol": "http",
							"host": [
								"localhost"
							],
							"port": "8080",
							"path": [
								"typeUser",
								"1"
							]
						}
					},
					"response": []
				},
				{
					"name": "6.TypeUser - Delete",
					"request": {
						"method": "DELETE",
						"header": [],
						"url": {
							"raw": "http://localhost:8080/typeUser/1",
							"protocol": "http",
							"host": [
								"localhost"
							],
							"port": "8080",
							"path": [
								"typeUser",
								"1"
							]
						}
					},
					"response": []
				}
			]
		},
		{
			"name": "👤 User Management",
			"item": [
				{
					"name": "1. Create User (Cliente)",
					"event": [
						{
							"listen": "test",
							"script": {
								"exec": [
									"if (pm.response.code === 201) {",
									"    var jsonData = pm.response.json();",
									"    pm.collectionVariables.set('userId', jsonData.id);",
									"    pm.test('User created successfully', function () {",
									"        pm.expect(pm.response.code).to.eql(201);",
									"    });",
									"} else {",
									"    pm.test('Failed to create user', function () {",
									"        pm.expect(pm.response.code).to.be.oneOf([400, 409]);",
									"    });",
									"}"
								],
								"type": "text/javascript"
							}
						}
					],
					"request": {
						"method": "POST",
						"header": [
							{
								"key": "Content-Type",
								"value": "application/json"
							},
							{
								"key": "Accept",
								"value": "application/json"
							}
						],
						"body": {
							"mode": "raw",
							"raw": "{\n  \"nome\": \"João Silva\",\n  \"email\": \"joao.silva@email.com\",\n  \"login\": \"joao.silva\",\n  \"senha\": \"senha12345678\",\n  \"dataAlteracao\": \"2025-07-12\",\n  \"tipo\": \"CLIENTE\",\n  \"address\": [\n    {\n      \"rua\": \"Rua das Flores\",\n      \"bairro\": \"Centro\",\n      \"complemento\": \"Apto 101\",\n      \"numero\": 123,\n      \"estado\": \"São Paulo\",\n      \"cidade\": \"São Paulo\",\n      \"cep\": \"01234567\"\n    }\n  ]\n}",
							"options": {
								"raw": {
									"language": "json"
								}
							}
						},
						"url": {
							"raw": "{{baseUrl}}/users",
							"host": [
								"{{baseUrl}}"
							],
							"path": [
								"users"
							]
						},
						"description": "Criar um novo usuário do tipo CLIENTE"
					},
					"response": []
				},
				{
					"name": "2. Create User (Dono Restaurante)",
					"event": [
						{
							"listen": "test",
							"script": {
								"exec": [
									"if (pm.response.code === 201) {",
									"    pm.test('Restaurant owner created successfully', function () {",
									"        pm.expect(pm.response.code).to.eql(201);",
									"    });",
									"} else {",
									"    pm.test('Failed to create restaurant owner', function () {",
									"        pm.expect(pm.response.code).to.be.oneOf([400, 409]);",
									"    });",
									"}"
								],
								"type": "text/javascript"
							}
						}
					],
					"request": {
						"method": "POST",
						"header": [
							{
								"key": "Content-Type",
								"value": "application/json"
							},
							{
								"key": "Accept",
								"value": "application/json"
							}
						],
						"body": {
							"mode": "raw",
							"raw": "{\n  \"nome\": \"Maria Santos\",\n  \"email\": \"maria.santos@restaurante.com\",\n  \"login\": \"maria.santos\",\n  \"senha\": \"donorestaurante123\",\n  \"dataAlteracao\": \"2025-07-12\",\n  \"tipo\": \"DONO\",\n  \"address\": [\n    {\n      \"rua\": \"Av. Paulista\",\n      \"bairro\": \"Bela Vista\",\n      \"complemento\": \"Sala 1001\",\n      \"numero\": 1000,\n      \"estado\": \"São Paulo\",\n      \"cidade\": \"São Paulo\",\n      \"cep\": \"01310100\"\n    }\n  ]\n}",
							"options": {
								"raw": {
									"language": "json"
								}
							}
						},
						"url": {
							"raw": "{{baseUrl}}/users",
							"host": [
								"{{baseUrl}}"
							],
							"path": [
								"users"
							]
						},
						"description": "Criar um novo usuário do tipo DONO (proprietário de restaurante)"
					},
					"response": []
				},
				{
					"name": "3. Get All Users",
					"event": [
						{
							"listen": "test",
							"script": {
								"exec": [
									"pm.test('Status code is 200', function () {",
									"    pm.response.to.have.status(200);",
									"});",
									"",
									"pm.test('Response is an array', function () {",
									"    var jsonData = pm.response.json();",
									"    pm.expect(jsonData).to.be.an('array');",
									"});"
								],
								"type": "text/javascript"
							}
						}
					],
					"request": {
						"method": "GET",
						"header": [
							{
								"key": "Accept",
								"value": "application/json"
							}
						],
						"url": {
							"raw": "{{baseUrl}}/users",
							"host": [
								"{{baseUrl}}"
							],
							"path": [
								"users"
							]
						},
						"description": "Listar todos os usuários cadastrados"
					},
					"response": []
				},
				{
					"name": "4. Get User by ID",
					"event": [
						{
							"listen": "test",
							"script": {
								"exec": [
									"if (pm.response.code === 200) {",
									"    pm.test('User found successfully', function () {",
									"        pm.expect(pm.response.code).to.eql(200);",
									"        var jsonData = pm.response.json();",
									"        pm.expect(jsonData).to.have.property('id');",
									"        pm.expect(jsonData).to.have.property('nome');",
									"        pm.expect(jsonData).to.have.property('email');",
									"    });",
									"} else {",
									"    pm.test('User not found', function () {",
									"        pm.expect(pm.response.code).to.eql(404);",
									"    });",
									"}"
								],
								"type": "text/javascript"
							}
						}
					],
					"request": {
						"method": "GET",
						"header": [
							{
								"key": "Accept",
								"value": "application/json"
							}
						],
						"url": {
							"raw": "{{baseUrl}}/users/{{userId}}",
							"host": [
								"{{baseUrl}}"
							],
							"path": [
								"users",
								"{{userId}}"
							]
						},
						"description": "Buscar usuário específico por ID"
					},
					"response": []
				},
				{
					"name": "5. Update User",
					"event": [
						{
							"listen": "test",
							"script": {
								"exec": [
									"if (pm.response.code === 200) {",
									"    pm.test('User updated successfully', function () {",
									"        pm.expect(pm.response.code).to.eql(200);",
									"    });",
									"} else {",
									"    pm.test('Failed to update user', function () {",
									"        pm.expect(pm.response.code).to.be.oneOf([400, 404]);",
									"    });",
									"}"
								],
								"type": "text/javascript"
							}
						}
					],
					"request": {
						"method": "PUT",
						"header": [
							{
								"key": "Content-Type",
								"value": "application/json"
							},
							{
								"key": "Accept",
								"value": "application/json"
							}
						],
						"body": {
							"mode": "raw",
							"raw": "{\n  \"nome\": \"João Silva Santos\",\n  \"email\": \"joao.silva@email.com\",\n  \"login\": \"joao.silva\",\n  \"senha\": \"novaSenhaAtualizada123\",\n  \"dataAlteracao\": \"2025-07-12\",\n  \"tipo\": \"CLIENTE\",\n  \"address\": [\n    {\n      \"rua\": \"Rua das Flores\",\n      \"bairro\": \"Centro\",\n      \"complemento\": \"Apto 201\",\n      \"numero\": 123,\n      \"estado\": \"São Paulo\",\n      \"cidade\": \"São Paulo\",\n      \"cep\": \"01234567\"\n    }\n  ]\n}",
							"options": {
								"raw": {
									"language": "json"
								}
							}
						},
						"url": {
							"raw": "{{baseUrl}}/users/{{userId}}",
							"host": [
								"{{baseUrl}}"
							],
							"path": [
								"users",
								"{{userId}}"
							]
						},
						"description": "Atualizar informações de um usuário existente"
					},
					"response": []
				},
				{
					"name": "6. Delete User",
					"event": [
						{
							"listen": "test",
							"script": {
								"exec": [
									"if (pm.response.code === 204) {",
									"    pm.test('User deleted successfully', function () {",
									"        pm.expect(pm.response.code).to.eql(204);",
									"    });",
									"} else {",
									"    pm.test('Failed to delete user', function () {",
									"        pm.expect(pm.response.code).to.be.oneOf([404, 400]);",
									"    });",
									"}"
								],
								"type": "text/javascript"
							}
						}
					],
					"request": {
						"method": "DELETE",
						"header": [
							{
								"key": "Accept",
								"value": "application/json"
							}
						],
						"url": {
							"raw": "{{baseUrl}}/users/{{userId}}",
							"host": [
								"{{baseUrl}}"
							],
							"path": [
								"users",
								"{{userId}}"
							]
						},
						"description": "Remover um usuário do sistema"
					},
					"response": []
				}
			],
			"description": "Endpoints para gestão de usuários (CRUD completo)"
		},
		{
			"name": "🍽️ Restaurant Management",
			"item": [
				{
					"name": "1. Create Restaurant",
					"event": [
						{
							"listen": "test",
							"script": {
								"exec": [
									"if (pm.response.code === 201) {",
									"    var jsonData = pm.response.json();",
									"    pm.collectionVariables.set('restaurantId', jsonData.id);",
									"    pm.test('Restaurant created successfully', function () {",
									"        pm.expect(pm.response.code).to.eql(201);",
									"        pm.expect(jsonData).to.have.property('id');",
									"        pm.expect(jsonData).to.have.property('name');",
									"        pm.expect(jsonData).to.have.property('owner');",
									"    });",
									"} else {",
									"    pm.test('Failed to create restaurant', function () {",
									"        pm.expect(pm.response.code).to.be.oneOf([400, 404, 409]);",
									"    });",
									"}"
								],
								"type": "text/javascript"
							}
						}
					],
					"request": {
						"method": "POST",
						"header": [
							{
								"key": "Content-Type",
								"value": "application/json"
							},
							{
								"key": "Accept",
								"value": "application/json"
							}
						],
						"body": {
							"mode": "raw",
							"raw": "{\n  \"name\": \"Restaurante Fortaleza de Sabor\",\n  \"kitchenType\": \"Brasileira Contemporânea\",\n  \"email\": \"maria.santos@restaurante.com\",\n  \"address\": [\n    {\n      \"rua\": \"Rua dos Sabores\",\n      \"bairro\": \"Vila Madalena\",\n      \"complemento\": \"Térreo\",\n      \"numero\": 456,\n      \"estado\": \"São Paulo\",\n      \"cidade\": \"São Paulo\",\n      \"cep\": \"05433000\"\n    }\n  ],\n  \"businessHours\": [\n    {\n      \"dayOfWeek\": \"MONDAY\",\n      \"openingTime\": \"11:00:00\",\n      \"closingTime\": \"23:00:00\",\n      \"observations\": \"Segunda-feira funcionamento normal\"\n    },\n    {\n      \"dayOfWeek\": \"TUESDAY\",\n      \"openingTime\": \"11:00:00\",\n      \"closingTime\": \"23:00:00\",\n      \"observations\": \"Terça-feira funcionamento normal\"\n    },\n    {\n      \"dayOfWeek\": \"WEDNESDAY\",\n      \"openingTime\": \"11:00:00\",\n      \"closingTime\": \"23:00:00\",\n      \"observations\": \"Quarta-feira funcionamento normal\"\n    },\n    {\n      \"dayOfWeek\": \"THURSDAY\",\n      \"openingTime\": \"11:00:00\",\n      \"closingTime\": \"23:00:00\",\n      \"observations\": \"Quinta-feira funcionamento normal\"\n    },\n    {\n      \"dayOfWeek\": \"FRIDAY\",\n      \"openingTime\": \"11:00:00\",\n      \"closingTime\": \"00:00:00\",\n      \"observations\": \"Sexta-feira até meia-noite\"\n    },\n    {\n      \"dayOfWeek\": \"SATURDAY\",\n      \"openingTime\": \"12:00:00\",\n      \"closingTime\": \"00:00:00\",\n      \"observations\": \"Sábado funcionamento especial\"\n    },\n    {\n      \"dayOfWeek\": \"SUNDAY\",\n      \"openingTime\": \"12:00:00\",\n      \"closingTime\": \"22:00:00\",\n      \"observations\": \"Domingo funcionamento reduzido\"\n    }\n  ]\n}",
							"options": {
								"raw": {
									"language": "json"
								}
							}
						},
						"url": {
							"raw": "{{baseUrl}}/restaurants",
							"host": [
								"{{baseUrl}}"
							],
							"path": [
								"restaurants"
							]
						},
						"description": "Criar um novo restaurante (requer usuário DONO)"
					},
					"response": []
				},
				{
					"name": "2. Create Restaurant - Multiple Addresses",
					"event": [
						{
							"listen": "test",
							"script": {
								"exec": [
									"if (pm.response.code === 201) {",
									"    pm.test('Restaurant with multiple addresses created successfully', function () {",
									"        pm.expect(pm.response.code).to.eql(201);",
									"    });",
									"} else {",
									"    pm.test('Failed to create restaurant', function () {",
									"        pm.expect(pm.response.code).to.be.oneOf([400, 404, 409]);",
									"    });",
									"}"
								],
								"type": "text/javascript"
							}
						}
					],
					"request": {
						"method": "POST",
						"header": [
							{
								"key": "Content-Type",
								"value": "application/json"
							},
							{
								"key": "Accept",
								"value": "application/json"
							}
						],
						"body": {
							"mode": "raw",
							"raw": "{\n  \"name\": \"Rede Sabor Brasileiro\",\n  \"kitchenType\": \"Regional Nordestina\",\n  \"email\": \"maria.santos@restaurante.com\",\n  \"address\": [\n    {\n      \"rua\": \"Rua Principal\",\n      \"bairro\": \"Centro\",\n      \"complemento\": \"Loja 1\",\n      \"numero\": 100,\n      \"estado\": \"São Paulo\",\n      \"cidade\": \"São Paulo\",\n      \"cep\": \"01000000\"\n    },\n    {\n      \"rua\": \"Av. Secundária\",\n      \"bairro\": \"Bairro Novo\",\n      \"complemento\": \"Loja 2\",\n      \"numero\": 200,\n      \"estado\": \"São Paulo\",\n      \"cidade\": \"São Paulo\",\n      \"cep\": \"02000000\"\n    }\n  ],\n  \"businessHours\": [\n    {\n      \"dayOfWeek\": \"MONDAY\",\n      \"openingTime\": \"10:00:00\",\n      \"closingTime\": \"22:00:00\",\n      \"observations\": \"Funcionamento padrão\"\n    },\n    {\n      \"dayOfWeek\": \"SUNDAY\",\n      \"openingTime\": \"11:00:00\",\n      \"closingTime\": \"21:00:00\",\n      \"observations\": \"Domingo reduzido\"\n    }\n  ]\n}",
							"options": {
								"raw": {
									"language": "json"
								}
							}
						},
						"url": {
							"raw": "{{baseUrl}}/restaurants",
							"host": [
								"{{baseUrl}}"
							],
							"path": [
								"restaurants"
							]
						},
						"description": "Criar restaurante com múltiplos endereços (rede)"
					},
					"response": []
				},
				{
					"name": "3. Update Restaurant",
					"event": [
						{
							"listen": "test",
							"script": {
								"exec": [
									"if (pm.response.code === 202) {",
									"    pm.test('Restaurant updated successfully', function () {",
									"        pm.expect(pm.response.code).to.eql(202);",
									"    });",
									"} else {",
									"    pm.test('Failed to update restaurant', function () {",
									"        pm.expect(pm.response.code).to.be.oneOf([400, 404, 409]);",
									"    });",
									"}"
								],
								"type": "text/javascript"
							}
						}
					],
					"request": {
						"method": "PUT",
						"header": [
							{
								"key": "Content-Type",
								"value": "application/json"
							},
							{
								"key": "Accept",
								"value": "application/json"
							}
						],
						"body": {
							"mode": "raw",
							"raw": "{\n  \"name\": \"Restaurante Fortaleza de Sabor - Atualizado\",\n  \"kitchenType\": \"Brasileira Gourmet\",\n  \"email\": \"maria.santos@restaurante.com\",\n  \"address\": [\n    {\n      \"rua\": \"Rua dos Sabores Especiais\",\n      \"bairro\": \"Vila Madalena\",\n      \"complemento\": \"Térreo - Novo Layout\",\n      \"numero\": 456,\n      \"estado\": \"São Paulo\",\n      \"cidade\": \"São Paulo\",\n      \"cep\": \"05433000\"\n    }\n  ],\n  \"businessHours\": [\n    {\n      \"dayOfWeek\": \"MONDAY\",\n      \"openingTime\": \"12:00:00\",\n      \"closingTime\": \"23:30:00\",\n      \"observations\": \"Horário estendido Segunda\"\n    },\n    {\n      \"dayOfWeek\": \"FRIDAY\",\n      \"openingTime\": \"12:00:00\",\n      \"closingTime\": \"01:00:00\",\n      \"observations\": \"Sexta-feira até 1h\"\n    },\n    {\n      \"dayOfWeek\": \"SATURDAY\",\n      \"openingTime\": \"13:00:00\",\n      \"closingTime\": \"01:00:00\",\n      \"observations\": \"Sábado funcionamento especial\"\n    }\n  ]\n}",
							"options": {
								"raw": {
									"language": "json"
								}
							}
						},
						"url": {
							"raw": "{{baseUrl}}/restaurants/{{restaurantId}}",
							"host": [
								"{{baseUrl}}"
							],
							"path": [
								"restaurants",
								"{{restaurantId}}"
							]
						},
						"description": "Atualizar informações de um restaurante existente"
					},
					"response": []
				}
			],
			"description": "Endpoints para gestão de restaurantes"
		},
		{
			"name": "🔐 Authentication",
			"item": [
				{
					"name": "1. Login User",
					"event": [
						{
							"listen": "test",
							"script": {
								"exec": [
									"if (pm.response.code === 200) {",
									"    var jsonData = pm.response.json();",
									"    if (jsonData.accessToken) {",
									"        pm.collectionVariables.set('authToken', jsonData.accessToken);",
									"    }",
									"    pm.test('Login successful', function () {",
									"        pm.expect(pm.response.code).to.eql(200);",
									"        pm.expect(jsonData).to.have.property('accessToken');",
									"    });",
									"} else {",
									"    pm.test('Login failed', function () {",
									"        pm.expect(pm.response.code).to.be.oneOf([401, 400]);",
									"    });",
									"}"
								],
								"type": "text/javascript"
							}
						}
					],
					"request": {
						"method": "POST",
						"header": [
							{
								"key": "Content-Type",
								"value": "application/json"
							},
							{
								"key": "Accept",
								"value": "application/json"
							}
						],
						"body": {
							"mode": "raw",
							"raw": "{\n  \"email\": \"joao.silva@email.com\",\n  \"password\": \"senha12345678\"\n}",
							"options": {
								"raw": {
									"language": "json"
								}
							}
						},
						"url": {
							"raw": "{{baseUrl}}/auth/login",
							"host": [
								"{{baseUrl}}"
							],
							"path": [
								"auth",
								"login"
							]
						},
						"description": "Realizar login e obter token de acesso"
					},
					"response": []
				},
				{
					"name": "2. Login Restaurant Owner",
					"event": [
						{
							"listen": "test",
							"script": {
								"exec": [
									"if (pm.response.code === 200) {",
									"    var jsonData = pm.response.json();",
									"    if (jsonData.accessToken) {",
									"        pm.collectionVariables.set('authToken', jsonData.accessToken);",
									"    }",
									"    pm.test('Restaurant owner login successful', function () {",
									"        pm.expect(pm.response.code).to.eql(200);",
									"        pm.expect(jsonData).to.have.property('accessToken');",
									"    });",
									"} else {",
									"    pm.test('Restaurant owner login failed', function () {",
									"        pm.expect(pm.response.code).to.be.oneOf([401, 400]);",
									"    });",
									"}"
								],
								"type": "text/javascript"
							}
						}
					],
					"request": {
						"method": "POST",
						"header": [
							{
								"key": "Content-Type",
								"value": "application/json"
							},
							{
								"key": "Accept",
								"value": "application/json"
							}
						],
						"body": {
							"mode": "raw",
							"raw": "{\n  \"email\": \"maria.santos@restaurante.com\",\n  \"password\": \"donorestaurante123\"\n}",
							"options": {
								"raw": {
									"language": "json"
								}
							}
						},
						"url": {
							"raw": "{{baseUrl}}/auth/login",
							"host": [
								"{{baseUrl}}"
							],
							"path": [
								"auth",
								"login"
							]
						},
						"description": "Login como proprietário de restaurante"
					},
					"response": []
				},
				{
					"name": "3. Update Password",
					"event": [
						{
							"listen": "test",
							"script": {
								"exec": [
									"if (pm.response.code === 204) {",
									"    pm.test('Password updated successfully', function () {",
									"        pm.expect(pm.response.code).to.eql(204);",
									"    });",
									"} else {",
									"    pm.test('Failed to update password', function () {",
									"        pm.expect(pm.response.code).to.be.oneOf([400, 404]);",
									"    });",
									"}"
								],
								"type": "text/javascript"
							}
						}
					],
					"request": {
						"method": "PATCH",
						"header": [
							{
								"key": "Content-Type",
								"value": "application/json"
							},
							{
								"key": "Accept",
								"value": "application/json"
							}
						],
						"body": {
							"mode": "raw",
							"raw": "{\n  \"email\": \"joao.silva@email.com\",\n  \"password\": \"novaSenhaSegura456\"\n}",
							"options": {
								"raw": {
									"language": "json"
								}
							}
						},
						"url": {
							"raw": "{{baseUrl}}/auth/password",
							"host": [
								"{{baseUrl}}"
							],
							"path": [
								"auth",
								"password"
							]
						},
						"description": "Alterar senha de um usuário"
					},
					"response": []
				}
			],
			"description": "Endpoints para autenticação e gestão de senhas"
		},
		{
			"name": "📜Menu",
			"item": [
				{
					"name": "1. Create Menu",
					"request": {
						"method": "POST",
						"header": [],
						"body": {
							"mode": "raw",
							"raw": "{\r\n    \"nome\": \"Bife à Milanesa\", \r\n    \"itemDescription\": \"O bife à milanesa é um prato que consiste em bifes de carne (geralmente vitela, mas pode ser de outros tipos) empanados e fritos.\", \r\n    \"itemPrice\": \"90.00\", \r\n    \"availability\": true, \r\n    \"itemImage\": \"https://encrypted-tbn0.gstatic.com/images?q=tbn:ANd9GcRrnjMkD-txjCuObAlFOdCCEZTMyyr9_W1eOA&s\"\r\n}",
							"options": {
								"raw": {
									"language": "json"
								}
							}
						},
						"url": {
							"raw": "{{baseUrl}}/cardapio",
							"host": [
								"{{baseUrl}}"
							],
							"path": [
								"cardapio"
							]
						}
					},
					"response": []
				},
				{
					"name": "2. Get All Menus",
					"protocolProfileBehavior": {
						"disableBodyPruning": true
					},
					"request": {
						"method": "GET",
						"header": [
							{
								"key": "Content-Type",
								"value": "application/json"
							}
						],
						"body": {
							"mode": "raw",
							"raw": ""
						},
						"url": {
							"raw": "{{baseUrl}}/cardapio",
							"host": [
								"{{baseUrl}}"
							],
							"path": [
								"cardapio"
							]
						}
					},
					"response": []
				},
				{
					"name": "3. Get Menu by ID",
					"protocolProfileBehavior": {
						"disableBodyPruning": true
					},
					"request": {
						"method": "GET",
						"header": [],
						"body": {
							"mode": "raw",
							"raw": "",
							"options": {
								"raw": {
									"language": "json"
								}
							}
						},
						"url": {
							"raw": "{{baseUrl}}/cardapio/{{menuId}}",
							"host": [
								"{{baseUrl}}"
							],
							"path": [
								"cardapio",
								"{{menuId}}"
							]
						}
					},
					"response": []
				},
				{
					"name": "4. Update Menu",
					"request": {
						"method": "PUT",
						"header": [],
						"body": {
							"mode": "raw",
							"raw": "{\r\n    \"nome\": \"Bife à Parmegiana\", \r\n    \"itemDescription\": \"O bife à milanesa é um prato que consiste em bifes de carne (geralmente vitela, mas pode ser de outros tipos) empanados e fritos. A carne é temperada, passada em farinha de trigo, em seguida em ovos batidos.\", \r\n    \"itemPrice\": \"90.00\", \r\n    \"availability\": true, \r\n    \"itemImage\": \"https://encrypted-tbn0.gstatic.com/images?q=tbn:ANd9GcRrnjMkD-txjCuObAlFOdCCEZTMyyr9_W1eOA&s\"\r\n}",
							"options": {
								"raw": {
									"language": "json"
								}
							}
						},
						"url": {
							"raw": "{{baseUrl}}/cardapio/{{menuId}}",
							"host": [
								"{{baseUrl}}"
							],
							"path": [
								"cardapio",
								"{{menuId}}"
							]
						}
					},
					"response": []
				},
				{
					"name": "5. Delete Menu",
					"request": {
						"method": "DELETE",
						"header": [],
						"url": {
							"raw": "{{baseUrl}}/cardapio/{{menuId}}",
							"host": [
								"{{baseUrl}}"
							],
							"path": [
								"cardapio",
								"{{menuId}}"
							]
						}
					},
					"response": []
				}
			],
			"description": "Endpoints para gestão de Cardápio (CRUD completo)"
		},
		{
			"name": "🧪 Test Scenarios",
			"item": [
				{
					"name": "Error Tests",
					"item": [
						{
							"name": "Create User - Invalid Email",
							"event": [
								{
									"listen": "test",
									"script": {
										"exec": [
											"pm.test('Invalid email should return 400', function () {",
											"    pm.expect(pm.response.code).to.eql(400);",
											"});"
										],
										"type": "text/javascript"
									}
								}
							],
							"request": {
								"method": "POST",
								"header": [
									{
										"key": "Content-Type",
										"value": "application/json"
									}
								],
								"body": {
									"mode": "raw",
									"raw": "{\n  \"nome\": \"Teste Email Inválido\",\n  \"email\": \"email-invalido\",\n  \"login\": \"teste\",\n  \"senha\": \"senha123\",\n  \"tipo\": \"CLIENTE\",\n  \"address\": []\n}",
									"options": {
										"raw": {
											"language": "json"
										}
									}
								},
								"url": {
									"raw": "{{baseUrl}}/users",
									"host": [
										"{{baseUrl}}"
									],
									"path": [
										"users"
									]
								},
								"description": "Testar criação de usuário com email inválido"
							},
							"response": []
						},
						{
							"name": "Create Restaurant - Nonexistent Owner",
							"event": [
								{
									"listen": "test",
									"script": {
										"exec": [
											"pm.test('Nonexistent owner should return 404', function () {",
											"    pm.expect(pm.response.code).to.eql(404);",
											"});"
										],
										"type": "text/javascript"
									}
								}
							],
							"request": {
								"method": "POST",
								"header": [
									{
										"key": "Content-Type",
										"value": "application/json"
									}
								],
								"body": {
									"mode": "raw",
									"raw": "{\n  \"name\": \"Restaurante Inexistente\",\n  \"kitchenType\": \"Teste\",\n  \"email\": \"dono.inexistente@email.com\",\n  \"address\": [],\n  \"businessHours\": []\n}",
									"options": {
										"raw": {
											"language": "json"
										}
									}
								},
								"url": {
									"raw": "{{baseUrl}}/restaurants",
									"host": [
										"{{baseUrl}}"
									],
									"path": [
										"restaurants"
									]
								},
								"description": "Testar criação de restaurante com dono inexistente"
							},
							"response": []
						},
						{
							"name": "Login - Invalid Credentials",
							"event": [
								{
									"listen": "test",
									"script": {
										"exec": [
											"pm.test('Invalid credentials should return 401', function () {",
											"    pm.expect(pm.response.code).to.eql(401);",
											"});"
										],
										"type": "text/javascript"
									}
								}
							],
							"request": {
								"method": "POST",
								"header": [
									{
										"key": "Content-Type",
										"value": "application/json"
									}
								],
								"body": {
									"mode": "raw",
									"raw": "{\n  \"email\": \"usuario.inexistente@email.com\",\n  \"password\": \"senhaErrada\"\n}",
									"options": {
										"raw": {
											"language": "json"
										}
									}
								},
								"url": {
									"raw": "{{baseUrl}}/auth/login",
									"host": [
										"{{baseUrl}}"
									],
									"path": [
										"auth",
										"login"
									]
								},
								"description": "Testar login com credenciais inválidas"
							},
							"response": []
						}
					],
					"description": "Testes de cenários de erro"
				},
				{
					"name": "Validation Tests",
					"item": [
						{
							"name": "Create User - Short Password",
							"event": [
								{
									"listen": "test",
									"script": {
										"exec": [
											"pm.test('Short password should return 400', function () {",
											"    pm.expect(pm.response.code).to.eql(400);",
											"});",
											"",
											"pm.test('Response should contain validation error', function () {",
											"    var jsonData = pm.response.json();",
											"    pm.expect(jsonData).to.have.property('errors');",
											"});"
										],
										"type": "text/javascript"
									}
								}
							],
							"request": {
								"method": "POST",
								"header": [
									{
										"key": "Content-Type",
										"value": "application/json"
									}
								],
								"body": {
									"mode": "raw",
									"raw": "{\n  \"nome\": \"Usuario Teste\",\n  \"email\": \"senha.curta@email.com\",\n  \"login\": \"senhacurta\",\n  \"senha\": \"123\",\n  \"dataAlteracao\": \"2025-07-12\",\n  \"tipo\": \"CLIENTE\",\n  \"address\": [\n    {\n      \"rua\": \"Rua Teste\",\n      \"bairro\": \"Centro\",\n      \"complemento\": \"Apto 101\",\n      \"numero\": 123,\n      \"estado\": \"São Paulo\",\n      \"cidade\": \"São Paulo\",\n      \"cep\": \"01234567\"\n    }\n  ]\n}",
									"options": {
										"raw": {
											"language": "json"
										}
									}
								},
								"url": {
									"raw": "{{baseUrl}}/users",
									"host": [
										"{{baseUrl}}"
									],
									"path": [
										"users"
									]
								},
								"description": "Testar criação de usuário com senha muito curta"
							},
							"response": []
						},
						{
							"name": "Create User - Invalid CEP",
							"event": [
								{
									"listen": "test",
									"script": {
										"exec": [
											"pm.test('Invalid CEP should return 400', function () {",
											"    pm.expect(pm.response.code).to.eql(400);",
											"});"
										],
										"type": "text/javascript"
									}
								}
							],
							"request": {
								"method": "POST",
								"header": [
									{
										"key": "Content-Type",
										"value": "application/json"
									}
								],
								"body": {
									"mode": "raw",
									"raw": "{\n  \"nome\": \"Usuario CEP Invalido\",\n  \"email\": \"cep.invalido@email.com\",\n  \"login\": \"cepinvalido\",\n  \"senha\": \"senha12345678\",\n  \"dataAlteracao\": \"2025-07-12\",\n  \"tipo\": \"CLIENTE\",\n  \"address\": [\n    {\n      \"rua\": \"Rua Teste\",\n      \"bairro\": \"Centro\",\n      \"complemento\": \"Apto 101\",\n      \"numero\": 123,\n      \"estado\": \"São Paulo\",\n      \"cidade\": \"São Paulo\",\n      \"cep\": \"123\"\n    }\n  ]\n}",
									"options": {
										"raw": {
											"language": "json"
										}
									}
								},
								"url": {
									"raw": "{{baseUrl}}/users",
									"host": [
										"{{baseUrl}}"
									],
									"path": [
										"users"
									]
								},
								"description": "Testar criação de usuário com CEP inválido"
							},
							"response": []
						},
						{
							"name": "Create User - Invalid Name Pattern",
							"event": [
								{
									"listen": "test",
									"script": {
										"exec": [
											"pm.test('Invalid name pattern should return 400', function () {",
											"    pm.expect(pm.response.code).to.eql(400);",
											"});"
										],
										"type": "text/javascript"
									}
								}
							],
							"request": {
								"method": "POST",
								"header": [
									{
										"key": "Content-Type",
										"value": "application/json"
									}
								],
								"body": {
									"mode": "raw",
									"raw": "{\n  \"nome\": \"Usuario123\",\n  \"email\": \"nome.invalido@email.com\",\n  \"login\": \"nomeinvalido\",\n  \"senha\": \"senha12345678\",\n  \"dataAlteracao\": \"2025-07-12\",\n  \"tipo\": \"CLIENTE\",\n  \"address\": [\n    {\n      \"rua\": \"Rua Teste\",\n      \"bairro\": \"Centro\",\n      \"complemento\": \"Apto 101\",\n      \"numero\": 123,\n      \"estado\": \"São Paulo\",\n      \"cidade\": \"São Paulo\",\n      \"cep\": \"01234567\"\n    }\n  ]\n}",
									"options": {
										"raw": {
											"language": "json"
										}
									}
								},
								"url": {
									"raw": "{{baseUrl}}/users",
									"host": [
										"{{baseUrl}}"
									],
									"path": [
										"users"
									]
								},
								"description": "Testar criação de usuário com nome contendo números"
							},
							"response": []
						},
						{
							"name": "Create User - Short Login",
							"event": [
								{
									"listen": "test",
									"script": {
										"exec": [
											"pm.test('Short login should return 400', function () {",
											"    pm.expect(pm.response.code).to.eql(400);",
											"});"
										],
										"type": "text/javascript"
									}
								}
							],
							"request": {
								"method": "POST",
								"header": [
									{
										"key": "Content-Type",
										"value": "application/json"
									}
								],
								"body": {
									"mode": "raw",
									"raw": "{\n  \"nome\": \"Usuario Login Curto\",\n  \"email\": \"login.curto@email.com\",\n  \"login\": \"ab\",\n  \"senha\": \"senha12345678\",\n  \"dataAlteracao\": \"2025-07-12\",\n  \"tipo\": \"CLIENTE\",\n  \"address\": [\n    {\n      \"rua\": \"Rua Teste\",\n      \"bairro\": \"Centro\",\n      \"complemento\": \"Apto 101\",\n      \"numero\": 123,\n      \"estado\": \"São Paulo\",\n      \"cidade\": \"São Paulo\",\n      \"cep\": \"01234567\"\n    }\n  ]\n}",
									"options": {
										"raw": {
											"language": "json"
										}
									}
								},
								"url": {
									"raw": "{{baseUrl}}/users",
									"host": [
										"{{baseUrl}}"
									],
									"path": [
										"users"
									]
								},
								"description": "Testar criação de usuário com login muito curto"
							},
							"response": []
						},
						{
							"name": "Create Restaurant - Short Kitchen Type",
							"event": [
								{
									"listen": "test",
									"script": {
										"exec": [
											"pm.test('Short kitchen type should return 400', function () {",
											"    pm.expect(pm.response.code).to.eql(400);",
											"});"
										],
										"type": "text/javascript"
									}
								}
							],
							"request": {
								"method": "POST",
								"header": [
									{
										"key": "Content-Type",
										"value": "application/json"
									}
								],
								"body": {
									"mode": "raw",
									"raw": "{\n  \"name\": \"Restaurante Tipo Cozinha Curto\",\n  \"kitchenType\": \"AA\",\n  \"email\": \"maria.santos@restaurante.com\",\n  \"address\": [\n    {\n      \"rua\": \"Rua Teste\",\n      \"bairro\": \"Centro\",\n      \"complemento\": \"Térreo\",\n      \"numero\": 123,\n      \"estado\": \"São Paulo\",\n      \"cidade\": \"São Paulo\",\n      \"cep\": \"01234567\"\n    }\n  ],\n  \"businessHours\": [\n    {\n      \"dayOfWeek\": \"MONDAY\",\n      \"openingTime\": \"11:00:00\",\n      \"closingTime\": \"23:00:00\",\n      \"observations\": \"Segunda-feira funcionamento normal\"\n    }\n  ]\n}",
									"options": {
										"raw": {
											"language": "json"
										}
									}
								},
								"url": {
									"raw": "{{baseUrl}}/restaurants",
									"host": [
										"{{baseUrl}}"
									],
									"path": [
										"restaurants"
									]
								},
								"description": "Testar criação de restaurante com tipo de cozinha muito curto"
							},
							"response": []
						},
						{
							"name": "Create Restaurant - Invalid Time Format",
							"event": [
								{
									"listen": "test",
									"script": {
										"exec": [
											"pm.test('Invalid time format should return 400', function () {",
											"    pm.expect(pm.response.code).to.eql(400);",
											"});"
										],
										"type": "text/javascript"
									}
								}
							],
							"request": {
								"method": "POST",
								"header": [
									{
										"key": "Content-Type",
										"value": "application/json"
									}
								],
								"body": {
									"mode": "raw",
									"raw": "{\n  \"name\": \"Restaurante Horario Invalido\",\n  \"kitchenType\": \"Cozinha de Teste\",\n  \"email\": \"maria.santos@restaurante.com\",\n  \"address\": [\n    {\n      \"rua\": \"Rua Teste\",\n      \"bairro\": \"Centro\",\n      \"complemento\": \"Térreo\",\n      \"numero\": 123,\n      \"estado\": \"São Paulo\",\n      \"cidade\": \"São Paulo\",\n      \"cep\": \"01234567\"\n    }\n  ],\n  \"businessHours\": [\n    {\n      \"dayOfWeek\": \"MONDAY\",\n      \"openingTime\": \"11:00\",\n      \"closingTime\": \"23:00\",\n      \"observations\": \"Horário com formato inválido\"\n    }\n  ]\n}",
									"options": {
										"raw": {
											"language": "json"
										}
									}
								},
								"url": {
									"raw": "{{baseUrl}}/restaurants",
									"host": [
										"{{baseUrl}}"
									],
									"path": [
										"restaurants"
									]
								},
								"description": "Testar criação de restaurante com formato de horário inválido"
							},
							"response": []
						}
					],
					"description": "Testes de validação de campos específicos"
				},
				{
					"name": "Business Logic Tests",
					"item": [
						{
							"name": "Create User - Duplicate Email",
							"event": [
								{
									"listen": "test",
									"script": {
										"exec": [
											"pm.test('Duplicate email should return 409', function () {",
											"    pm.expect(pm.response.code).to.eql(409);",
											"});"
										],
										"type": "text/javascript"
									}
								}
							],
							"request": {
								"method": "POST",
								"header": [
									{
										"key": "Content-Type",
										"value": "application/json"
									}
								],
								"body": {
									"mode": "raw",
									"raw": "{\n  \"nome\": \"Usuario Duplicado\",\n  \"email\": \"joao.silva@email.com\",\n  \"login\": \"joaoduplicado\",\n  \"senha\": \"senha12345678\",\n  \"dataAlteracao\": \"2025-07-12\",\n  \"tipo\": \"CLIENTE\",\n  \"address\": [\n    {\n      \"rua\": \"Rua Teste\",\n      \"bairro\": \"Centro\",\n      \"complemento\": \"Apto 101\",\n      \"numero\": 123,\n      \"estado\": \"São Paulo\",\n      \"cidade\": \"São Paulo\",\n      \"cep\": \"01234567\"\n    }\n  ]\n}",
									"options": {
										"raw": {
											"language": "json"
										}
									}
								},
								"url": {
									"raw": "{{baseUrl}}/users",
									"host": [
										"{{baseUrl}}"
									],
									"path": [
										"users"
									]
								},
								"description": "Testar criação de usuário com email já existente"
							},
							"response": []
						},
						{
							"name": "Update Non-existent User",
							"event": [
								{
									"listen": "test",
									"script": {
										"exec": [
											"pm.test('Update non-existent user should return 404', function () {",
											"    pm.expect(pm.response.code).to.eql(404);",
											"});"
										],
										"type": "text/javascript"
									}
								}
							],
							"request": {
								"method": "PUT",
								"header": [
									{
										"key": "Content-Type",
										"value": "application/json"
									}
								],
								"body": {
									"mode": "raw",
									"raw": "{\n  \"nome\": \"Usuario Inexistente\",\n  \"email\": \"inexistente@email.com\",\n  \"login\": \"inexistente\",\n  \"senha\": \"senha12345678\",\n  \"dataAlteracao\": \"2025-07-12\",\n  \"tipo\": \"CLIENTE\",\n  \"address\": [\n    {\n      \"rua\": \"Rua Teste\",\n      \"bairro\": \"Centro\",\n      \"complemento\": \"Apto 101\",\n      \"numero\": 123,\n      \"estado\": \"São Paulo\",\n      \"cidade\": \"São Paulo\",\n      \"cep\": \"01234567\"\n    }\n  ]\n}",
									"options": {
										"raw": {
											"language": "json"
										}
									}
								},
								"url": {
									"raw": "{{baseUrl}}/users/99999",
									"host": [
										"{{baseUrl}}"
									],
									"path": [
										"users",
										"99999"
									]
								},
								"description": "Testar atualização de usuário inexistente"
							},
							"response": []
						},
						{
							"name": "Delete Non-existent User",
							"event": [
								{
									"listen": "test",
									"script": {
										"exec": [
											"pm.test('Delete non-existent user should return 404', function () {",
											"    pm.expect(pm.response.code).to.eql(404);",
											"});"
										],
										"type": "text/javascript"
									}
								}
							],
							"request": {
								"method": "DELETE",
								"header": [],
								"url": {
									"raw": "{{baseUrl}}/users/99999",
									"host": [
										"{{baseUrl}}"
									],
									"path": [
										"users",
										"99999"
									]
								},
								"description": "Testar exclusão de usuário inexistente"
							},
							"response": []
						},
						{
							"name": "Get Non-existent User",
							"event": [
								{
									"listen": "test",
									"script": {
										"exec": [
											"pm.test('Get non-existent user should return 404', function () {",
											"    pm.expect(pm.response.code).to.eql(404);",
											"});"
										],
										"type": "text/javascript"
									}
								}
							],
							"request": {
								"method": "GET",
								"header": [],
								"url": {
									"raw": "{{baseUrl}}/users/99999",
									"host": [
										"{{baseUrl}}"
									],
									"path": [
										"users",
										"99999"
									]
								},
								"description": "Testar busca de usuário inexistente"
							},
							"response": []
						},
						{
							"name": "Update Non-existent Restaurant",
							"event": [
								{
									"listen": "test",
									"script": {
										"exec": [
											"pm.test('Update non-existent restaurant should return 404', function () {",
											"    pm.expect(pm.response.code).to.eql(404);",
											"});"
										],
										"type": "text/javascript"
									}
								}
							],
							"request": {
								"method": "PUT",
								"header": [
									{
										"key": "Content-Type",
										"value": "application/json"
									}
								],
								"body": {
									"mode": "raw",
									"raw": "{\n  \"name\": \"Restaurante Inexistente\",\n  \"kitchenType\": \"Cozinha Inexistente\",\n  \"email\": \"maria.santos@restaurante.com\",\n  \"address\": [\n    {\n      \"rua\": \"Rua Teste\",\n      \"bairro\": \"Centro\",\n      \"complemento\": \"Térreo\",\n      \"numero\": 123,\n      \"estado\": \"São Paulo\",\n      \"cidade\": \"São Paulo\",\n      \"cep\": \"01234567\"\n    }\n  ],\n  \"businessHours\": [\n    {\n      \"dayOfWeek\": \"MONDAY\",\n      \"openingTime\": \"11:00:00\",\n      \"closingTime\": \"23:00:00\",\n      \"observations\": \"Teste\"\n    }\n  ]\n}",
									"options": {
										"raw": {
											"language": "json"
										}
									}
								},
								"url": {
									"raw": "{{baseUrl}}/restaurants/99999",
									"host": [
										"{{baseUrl}}"
									],
									"path": [
										"restaurants",
										"99999"
									]
								},
								"description": "Testar atualização de restaurante inexistente"
							},
							"response": []
						}
					],
					"description": "Testes de lógica de negócio e recursos inexistentes"
				},
				{
					"name": "Edge Cases",
					"item": [
						{
							"name": "Create Restaurant - Empty Business Hours",
							"event": [
								{
									"listen": "test",
									"script": {
										"exec": [
											"pm.test('Empty business hours should be handled', function () {",
											"    pm.expect(pm.response.code).to.be.oneOf([201, 400]);",
											"});"
										],
										"type": "text/javascript"
									}
								}
							],
							"request": {
								"method": "POST",
								"header": [
									{
										"key": "Content-Type",
										"value": "application/json"
									}
								],
								"body": {
									"mode": "raw",
									"raw": "{\n  \"name\": \"Restaurante Sem Horários\",\n  \"kitchenType\": \"Experimental\",\n  \"email\": \"maria.santos@restaurante.com\",\n  \"address\": [\n    {\n      \"rua\": \"Rua Teste\",\n      \"bairro\": \"Teste\",\n      \"complemento\": \"\",\n      \"numero\": 1,\n      \"estado\": \"SP\",\n      \"cidade\": \"São Paulo\",\n      \"cep\": \"00000000\"\n    }\n  ],\n  \"businessHours\": []\n}",
									"options": {
										"raw": {
											"language": "json"
										}
									}
								},
								"url": {
									"raw": "{{baseUrl}}/restaurants",
									"host": [
										"{{baseUrl}}"
									],
									"path": [
										"restaurants"
									]
								},
								"description": "Testar criação de restaurante sem horários de funcionamento"
							},
							"response": []
						},
						{
							"name": "Create User - Minimal Data",
							"event": [
								{
									"listen": "test",
									"script": {
										"exec": [
											"pm.test('Minimal data should be handled', function () {",
											"    pm.expect(pm.response.code).to.be.oneOf([201, 400]);",
											"});"
										],
										"type": "text/javascript"
									}
								}
							],
							"request": {
								"method": "POST",
								"header": [
									{
										"key": "Content-Type",
										"value": "application/json"
									}
								],
								"body": {
									"mode": "raw",
									"raw": "{\n  \"nome\": \"A\",\n  \"email\": \"a@b.co\",\n  \"login\": \"a\",\n  \"senha\": \"123\",\n  \"tipo\": \"CLIENTE\",\n  \"address\": []\n}",
									"options": {
										"raw": {
											"language": "json"
										}
									}
								},
								"url": {
									"raw": "{{baseUrl}}/users",
									"host": [
										"{{baseUrl}}"
									],
									"path": [
										"users"
									]
								},
								"description": "Testar criação de usuário com dados mínimos"
							},
							"response": []
						}
					],
					"description": "Testes de casos extremos"
				},
				{
					"name": "Malformed Requests",
					"item": [
						{
							"name": "Create User - Missing Required Fields",
							"event": [
								{
									"listen": "test",
									"script": {
										"exec": [
											"pm.test('Missing required fields should return 400', function () {",
											"    pm.expect(pm.response.code).to.eql(400);",
											"});"
										],
										"type": "text/javascript"
									}
								}
							],
							"request": {
								"method": "POST",
								"header": [
									{
										"key": "Content-Type",
										"value": "application/json"
									}
								],
								"body": {
									"mode": "raw",
									"raw": "{\n  \"nome\": \"Usuario Incompleto\",\n  \"email\": \"incompleto@email.com\"\n}",
									"options": {
										"raw": {
											"language": "json"
										}
									}
								},
								"url": {
									"raw": "{{baseUrl}}/users",
									"host": [
										"{{baseUrl}}"
									],
									"path": [
										"users"
									]
								},
								"description": "Testar criação de usuário com campos obrigatórios ausentes"
							},
							"response": []
						},
						{
							"name": "Create User - Invalid JSON",
							"event": [
								{
									"listen": "test",
									"script": {
										"exec": [
											"pm.test('Invalid JSON should return 400', function () {",
											"    pm.expect(pm.response.code).to.eql(400);",
											"});"
										],
										"type": "text/javascript"
									}
								}
							],
							"request": {
								"method": "POST",
								"header": [
									{
										"key": "Content-Type",
										"value": "application/json"
									}
								],
								"body": {
									"mode": "raw",
									"raw": "{\n  \"nome\": \"Usuario JSON Invalido\",\n  \"email\": \"json.invalido@email.com\",\n  \"login\": \"jsoninvalido\",\n  \"senha\": \"senha12345678\",\n  \"tipo\": \"CLIENTE\",\n  \"address\": [\n    {\n      \"rua\": \"Rua Teste\",\n      \"bairro\": \"Centro\",\n      \"complemento\": \"Apto 101\",\n      \"numero\": \"123abc\",\n      \"estado\": \"São Paulo\",\n      \"cidade\": \"São Paulo\",\n      \"cep\": \"01234567\"\n    }\n  ]\n}",
									"options": {
										"raw": {
											"language": "json"
										}
									}
								},
								"url": {
									"raw": "{{baseUrl}}/users",
									"host": [
										"{{baseUrl}}"
									],
									"path": [
										"users"
									]
								},
								"description": "Testar criação de usuário com JSON mal formado"
							},
							"response": []
						},
						{
							"name": "Create Restaurant - Empty Name",
							"event": [
								{
									"listen": "test",
									"script": {
										"exec": [
											"pm.test('Empty name should return 400', function () {",
											"    pm.expect(pm.response.code).to.eql(400);",
											"});"
										],
										"type": "text/javascript"
									}
								}
							],
							"request": {
								"method": "POST",
								"header": [
									{
										"key": "Content-Type",
										"value": "application/json"
									}
								],
								"body": {
									"mode": "raw",
									"raw": "{\n  \"name\": \"\",\n  \"kitchenType\": \"Cozinha Teste\",\n  \"email\": \"maria.santos@restaurante.com\",\n  \"address\": [\n    {\n      \"rua\": \"Rua Teste\",\n      \"bairro\": \"Centro\",\n      \"complemento\": \"Térreo\",\n      \"numero\": 123,\n      \"estado\": \"São Paulo\",\n      \"cidade\": \"São Paulo\",\n      \"cep\": \"01234567\"\n    }\n  ],\n  \"businessHours\": []\n}",
									"options": {
										"raw": {
											"language": "json"
										}
									}
								},
								"url": {
									"raw": "{{baseUrl}}/restaurants",
									"host": [
										"{{baseUrl}}"
									],
									"path": [
										"restaurants"
									]
								},
								"description": "Testar criação de restaurante com nome vazio"
							},
							"response": []
						},
						{
							"name": "Login - Empty Body",
							"event": [
								{
									"listen": "test",
									"script": {
										"exec": [
											"pm.test('Empty body should return 400', function () {",
											"    pm.expect(pm.response.code).to.eql(400);",
											"});"
										],
										"type": "text/javascript"
									}
								}
							],
							"request": {
								"method": "POST",
								"header": [
									{
										"key": "Content-Type",
										"value": "application/json"
									}
								],
								"body": {
									"mode": "raw",
									"raw": "{}",
									"options": {
										"raw": {
											"language": "json"
										}
									}
								},
								"url": {
									"raw": "{{baseUrl}}/auth/login",
									"host": [
										"{{baseUrl}}"
									],
									"path": [
										"auth",
										"login"
									]
								},
								"description": "Testar login com corpo vazio"
							},
							"response": []
						},
						{
							"name": "Update Password - Invalid Email",
							"event": [
								{
									"listen": "test",
									"script": {
										"exec": [
											"pm.test('Invalid email for password update should return 404', function () {",
											"    pm.expect(pm.response.code).to.eql(404);",
											"});"
										],
										"type": "text/javascript"
									}
								}
							],
							"request": {
								"method": "PATCH",
								"header": [
									{
										"key": "Content-Type",
										"value": "application/json"
									}
								],
								"body": {
									"mode": "raw",
									"raw": "{\n  \"email\": \"usuario.inexistente@email.com\",\n  \"password\": \"novaSenhaSegura456\"\n}",
									"options": {
										"raw": {
											"language": "json"
										}
									}
								},
								"url": {
									"raw": "{{baseUrl}}/auth/password",
									"host": [
										"{{baseUrl}}"
									],
									"path": [
										"auth",
										"password"
									]
								},
								"description": "Testar alteração de senha com email inexistente"
							},
							"response": []
						}
					],
					"description": "Testes de requisições mal formadas"
				},
				{
					"name": "Security Tests",
					"item": [
						{
							"name": "Access Without Authentication",
							"event": [
								{
									"listen": "test",
									"script": {
										"exec": [
											"pm.test('Should handle unauthenticated access appropriately', function () {",
											"    pm.expect(pm.response.code).to.be.oneOf([200, 401, 403]);",
											"});"
										],
										"type": "text/javascript"
									}
								}
							],
							"request": {
								"method": "GET",
								"header": [],
								"url": {
									"raw": "{{baseUrl}}/users",
									"host": [
										"{{baseUrl}}"
									],
									"path": [
										"users"
									]
								},
								"description": "Testar acesso sem autenticação"
							},
							"response": []
						},
						{
							"name": "SQL Injection Test - Login",
							"event": [
								{
									"listen": "test",
									"script": {
										"exec": [
											"pm.test('SQL injection should be prevented', function () {",
											"    pm.expect(pm.response.code).to.be.oneOf([400, 401]);",
											"});"
										],
										"type": "text/javascript"
									}
								}
							],
							"request": {
								"method": "POST",
								"header": [
									{
										"key": "Content-Type",
										"value": "application/json"
									}
								],
								"body": {
									"mode": "raw",
									"raw": "{\n  \"email\": \"admin@test.com'; DROP TABLE users; --\",\n  \"password\": \"password\"\n}",
									"options": {
										"raw": {
											"language": "json"
										}
									}
								},
								"url": {
									"raw": "{{baseUrl}}/auth/login",
									"host": [
										"{{baseUrl}}"
									],
									"path": [
										"auth",
										"login"
									]
								},
								"description": "Testar prevenção de SQL injection"
							},
							"response": []
						},
						{
							"name": "XSS Test - User Creation",
							"event": [
								{
									"listen": "test",
									"script": {
										"exec": [
											"pm.test('XSS should be prevented', function () {",
											"    pm.expect(pm.response.code).to.be.oneOf([400, 201]);",
											"});"
										],
										"type": "text/javascript"
									}
								}
							],
							"request": {
								"method": "POST",
								"header": [
									{
										"key": "Content-Type",
										"value": "application/json"
									}
								],
								"body": {
									"mode": "raw",
									"raw": "{\n  \"nome\": \"<script>alert('XSS')</script>\",\n  \"email\": \"xss.test@email.com\",\n  \"login\": \"xsstest\",\n  \"senha\": \"senha12345678\",\n  \"dataAlteracao\": \"2025-07-12\",\n  \"tipo\": \"CLIENTE\",\n  \"address\": [\n    {\n      \"rua\": \"Rua Teste\",\n      \"bairro\": \"Centro\",\n      \"complemento\": \"Apto 101\",\n      \"numero\": 123,\n      \"estado\": \"São Paulo\",\n      \"cidade\": \"São Paulo\",\n      \"cep\": \"01234567\"\n    }\n  ]\n}",
									"options": {
										"raw": {
											"language": "json"
										}
									}
								},
								"url": {
									"raw": "{{baseUrl}}/users",
									"host": [
										"{{baseUrl}}"
									],
									"path": [
										"users"
									]
								},
								"description": "Testar prevenção de XSS em campos de entrada"
							},
							"response": []
						}
					],
					"description": "Testes de segurança básicos"
				}
			],
			"description": "Cenários de teste especiais"
		}
	],
	"auth": {
		"type": "bearer",
		"bearer": [
			{
				"key": "token",
				"value": "{{authToken}}",
				"type": "string"
			}
		]
	},
	"event": [
		{
			"listen": "prerequest",
			"script": {
				"type": "text/javascript",
				"exec": [
					""
				]
			}
		},
		{
			"listen": "test",
			"script": {
				"type": "text/javascript",
				"exec": [
					""
				]
			}
		}
	],
	"variable": [
		{
			"key": "baseUrl",
			"value": "http://localhost:8080",
			"type": "string"
		},
		{
			"key": "authToken",
			"value": "",
			"type": "string"
		},
		{
			"key": "userId",
			"value": "",
			"type": "string"
		},
		{
			"key": "restaurantId",
			"value": "",
			"type": "string"
		},
		{
			"key": "menuId",
			"value": "",
			"type": "default"
		}
	]
}